nlpguard/__init__.py
nlpguard/nlpguard.py
nlpguard/explainer/__init__.py
nlpguard/explainer/explainer.py
nlpguard/identifier/__init__.py
nlpguard/identifier/identifier.py
nlpguard/identifier/identifier_old.py
nlpguard/moderator/__init__.py
nlpguard/moderator/moderator.py
nlpguard-0.0.1.dist-info/LICENSE.md
nlpguard-0.0.1.dist-info/METADATA
nlpguard-0.0.1.dist-info/WHEEL
nlpguard-0.0.1.dist-info/top_level.txt
nlpguard-0.0.1.dist-info/RECORD
