Metadata-Version: 2.1
Name: nlpguard
Version: 0.0.1
Summary: NLPGuard: a Framework for Mitigating the use of Protected Attributes by NLP Classifiers
Home-page: https://github.com/grecosalvatore/nlpguard
Author: Salvatore Greco
Author-email: grecosalvatore94@gmail.com
Classifier: Programming Language :: Python :: 3
Classifier: Programming Language :: Python :: 3.9
Classifier: License :: OSI Approved :: MIT License
Classifier: Operating System :: OS Independent
Requires-Python: >=3.9
License-File: LICENSE.md
Requires-Dist: numpy>=1.22.4
Requires-Dist: scikit-learn>=0.24.2
Requires-Dist: matplotlib~=3.5.1
Requires-Dist: scipy>=1.10.0
Requires-Dist: tqdm~=4.64.1
Requires-Dist: setuptools~=58.0.4
Requires-Dist: openai~=1.3.9
Requires-Dist: pandas~=2.1.4
Requires-Dist: torch~=2.1.2
Requires-Dist: transformers~=4.48.1
